sbdscommons/__init__.py
sbdscommons/batch_transform.py
sbdscommons/build_model.py
sbdscommons/constants.py
sbdscommons/model/__init__.py
sbdscommons/model/base.py
sbdscommons/model/model.py
sbdscommons/params/__init__.py
sbdscommons/params/propensity.yaml
sbdscommons/query/propensity_model_input_template_query.sql
sbdscommons/query/propensity_predict_template_query.sql
sbdscommons/utils/__init__.py
sbdscommons/utils/yaml_utils.py
tests/__init__.py
sbdscommons-0.2.0.dist-info/LICENSE
sbdscommons-0.2.0.dist-info/METADATA
sbdscommons-0.2.0.dist-info/WHEEL
sbdscommons-0.2.0.dist-info/top_level.txt
sbdscommons-0.2.0.dist-info/RECORD
