Metadata-Version: 2.1
Name: sbdscommons
Version: 0.2.0
Summary: Packages shared between sb data science projects
Home-page: https://github.com/Snusbolaget/data-science
Author: Olof & Joseph
Author-email: olof.nilsson@snusbolaget.se
License: UNKNOWN
Platform: UNKNOWN
Classifier: Programming Language :: Python :: 3
Classifier: License :: OSI Approved :: MIT License
Classifier: Operating System :: OS Independent
